example/example.sv
module simple_circuit_prop_delay(A,B,C,D,E);
    output D,E;
    input A,B,C;
    wire w1;

    and #30 G1(w1,A,B);
    not #10 G2(D,w1);
    or  #20 G3(E,w1,C);
endmodule

example/test.sv
module t_simple_circuit_prop_delay;
    wire D,E;
    reg A,B,C;

    simple_circuit_prop_delay uut(A,B,C,D,E);

    initial 
        begin
        $dumpfile("t_simple_circuit_prop_delay.vcd");
        $dumpvars(0, t_simple_circuit_prop_delay);
        A=1'b0; B=1'b0; C=1'b0;
        #100 A = 1; B = 1; C = 1;
        end

    initial #200 $finish;
endmodule

example/t_simple_circuit_prop_delay.vcd
$date
	Fri Dec 22 20:35:52 2023
$end
$version
	Icarus Verilog
$end
$timescale
	1s
$end
$scope module t_simple_circuit_prop_delay $end
$var wire 1 ! E $end
$var wire 1 " D $end
$var reg 1 # A $end
$var reg 1 $ B $end
$var reg 1 % C $end
$scope module uut $end
$var wire 1 # A $end
$var wire 1 $ B $end
$var wire 1 % C $end
$var wire 1 " D $end
$var wire 1 ! E $end
$var wire 1 & w1 $end
$upscope $end
$upscope $end
$enddefinitions $end
#0
$dumpvars
x&
0%
0$
0#
x"
x!
$end
#30
0&
#40
1"
#50
0!
#100
1%
1$
1#
#120
1!
#130
1&
#140
0"
