simple/circuto_simple.sv
module circuito_simple(
    input A,B,C,
    output X,Y
    );
    wire e;
    or g1(A,B,e);
    not g2(Y,e);
    and g3(X,C,Y);
endmodule

simple/simple_tb.sv
module circ_simple;
    reg A;
    reg B;
    reg C;
    wire X;
    wire Y;

    circuito_simple cir1(.A(A), .B(B), .C(C), .X(X), .Y(Y));

    initial begin
      $dumpfile("circ_simple.vcd");
      $dumpvars(0, circ_simple);

      A = 1'b0; B = 1'b0; C = 1'b0;
      #10;
      A = 1'b0; B = 1'b0; C = 1'b1;
      #10;
      A = 1'b0; B = 1'b1; C = 1'b0;
      #10;
      A = 1'b0; B = 1'b1; C = 1'b1;
      #10;
      A = 1'b1; B = 1'b0; C = 1'b0;
      #10;
      A = 1'b1; B = 1'b0; C = 1'b1;
      #10;
      A = 1'b1; B = 1'b1; C = 1'b0;
      #10;
      A = 1'b1; B = 1'b1; C = 1'b1;
      #10;
      $finish;
    end

endmodule

simple/circ_simple.vcd
$date
	Wed Dec 13 23:54:39 2023
$end
$version
	Icarus Verilog
$end
$timescale
	1s
$end
$scope module circ_simple $end
$var wire 1 ! Y $end
$var wire 1 " X $end
$var reg 1 # A $end
$var reg 1 $ B $end
$var reg 1 % C $end
$scope module cir1 $end
$var wire 1 & A $end
$var wire 1 $ B $end
$var wire 1 % C $end
$var wire 1 " X $end
$var wire 1 ! Y $end
$var wire 1 ' e $end
$upscope $end
$upscope $end
$enddefinitions $end
#0
$dumpvars
z'
x&
0%
0$
0#
0"
z!
$end
#10
x"
1%
#20
0"
0%
1$
#30
x"
1%
#40
0"
0%
0$
x&
1#
#50
x"
1%
#60
0"
1&
0%
1$
#70
x"
1%
