helf_adder/helf_adder.sv
module helf_adder(a,b,sum,carry);
    input a, b;
    output sum, carry;

    // Ecuación lógica
    assign sum = a ^ b;
    assign carry = a & b;
endmodule

helf_adder/sumador_comp.sv
`include "helf_adder.sv"	
module sumador_comp(a,b,cin,sum,cout);
    input a,b,cin;
    output sum,cout;
    wire s1,c1,c2;
   
    helf_adder ms1 (a,b,s1,c1);
    helf_adder ms2 (s1,cin,sum,c2);
    assign cout = c1 | c2;
endmodule

helf_adder/test_adder.sv
module test_adder;
    reg a,b,cin;
    wire sum,cout;

    sumador_comp adder(a,b,cin,sum,cout);
    initial begin
        $dumpfile("test_adder.vcd");
        $dumpvars(0, test_adder);
        #10 a=0; b=0; cin=0;
        #10 a=0; b=0; cin=1;
        #10 a=0; b=1; cin=0;
        #10 a=0; b=1; cin=1;
        #10 a=1; b=0; cin=0;
        #10 a=1; b=0; cin=1;
        #10 a=1; b=1; cin=0;
        #10 a=1; b=1; cin=1;
        #10 $finish;
    end
endmodule

helf_adder/test_adder.vcd
$date
	Sat Dec 23 11:47:46 2023
$end
$version
	Icarus Verilog
$end
$timescale
	1s
$end
$scope module test_adder $end
$var wire 1 ! sum $end
$var wire 1 " cout $end
$var reg 1 # a $end
$var reg 1 $ b $end
$var reg 1 % cin $end
$scope module adder $end
$var wire 1 # a $end
$var wire 1 $ b $end
$var wire 1 % cin $end
$var wire 1 " cout $end
$var wire 1 ! sum $end
$var wire 1 & s1 $end
$var wire 1 ' c2 $end
$var wire 1 ( c1 $end
$scope module ms1 $end
$var wire 1 # a $end
$var wire 1 $ b $end
$var wire 1 ( carry $end
$var wire 1 & sum $end
$upscope $end
$scope module ms2 $end
$var wire 1 & a $end
$var wire 1 % b $end
$var wire 1 ' carry $end
$var wire 1 ! sum $end
$upscope $end
$upscope $end
$upscope $end
$enddefinitions $end
#0
$dumpvars
x(
x'
x&
x%
x$
x#
x"
x!
$end
#10
0!
0"
0&
0(
0'
0$
0#
0%
#20
1!
1&
1$
#30
0$
1#
#40
0!
1"
0&
1(
1$
#50
0"
0(
1!
0$
0#
1%
#60
1"
0!
1'
1&
1$
#70
0$
1#
#80
1!
0'
0&
1(
1$
