flip_flop_D/D.sv
module D_FF(Q,D,CLK);
    input D,CLK;
    output Q;
    reg Q;
    always @(posedge CLK) begin
        Q <= D;
    end
endmodule

flip_flop_D/testb_D.sv
module test_D_FF;
    reg D,CLK;
    wire Q;
    D_FF D_FF_0(Q,D,CLK);
    initial begin
        $dumpfile("test_D_FF.vcd");
        $dumpvars(0,test_D_FF);
        CLK = 1;
        forever #5 CLK = ~CLK;
    end
    initial begin
        D = 0;
        
        #5 D = 1;
        #5 D = 0;
        #5 D = 1;
        #5 D = 0;
        #5 D = 1;
        #5 D = 0;
        #5 D = 0;
        #5 D = 1;
        #5 D = 1;
        #5 D = 0;
        #5 D = 1;
        #5 D = 0;
        #5 D = 0;
        #5 D = 1;
        #5 D = 1;
        
        #5 $finish;
   
       
    end
    endmodule

flip_flop_D/test_D_FF.vcd
$date
	Fri Apr 19 15:05:32 2024
$end
$version
	Icarus Verilog
$end
$timescale
	1s
$end
$scope module test_D_FF $end
$var wire 1 ! Q $end
$var reg 1 " CLK $end
$var reg 1 # D $end
$scope module D_FF_0 $end
$var wire 1 " CLK $end
$var wire 1 # D $end
$var reg 1 ! Q $end
$upscope $end
$upscope $end
$enddefinitions $end
#0
$dumpvars
0#
1"
0!
$end
#5
1#
0"
#10
0#
1"
#15
1#
0"
#20
0#
1"
#25
1#
0"
#30
0#
1"
#35
0"
#40
1!
1#
1"
#45
0"
#50
0!
0#
1"
#55
1#
0"
#60
0#
1"
#65
0"
#70
1!
1#
1"
