ens/contador.v
module contador (
    input clk,    // Reloj de entrada
    input rst,    // Señal de reset
    output reg [2:0] count   // Salida del contador de 3 bits
);

    always @(posedge clk or posedge rst)
    begin
        if (rst)
            count <= 3'b000;
        else
            count <= count + 1;
    end

endmodule

ens/testbench_contador.v
`timescale 1ns / 1ps

module testbench_contador;

    reg clk;
    reg rst;
    wire [2:0] count;

    contador contador_inst (
        .clk(clk),
        .rst(rst),
        .count(count)
    );

    // Generar el reloj
    always #5 clk = ~clk;

    initial begin  
        // Iniciar la simulación VCD
        $dumpfile("contador.vcd");
        $dumpvars(0, testbench_contador);
        clk = 0;
        rst = 1;

        #10 rst = 0;
        #20;

      

        // Añadir una simulación de 100 unidades de tiempo (10ns)
        #100;

        // Mostrar valores durante la simulación
        $display("Tiempo\tValor del contador\tReloj\tReset");
        $monitor("%t\t%b\t\t\t%b\t%b", $time, count, clk, rst);

        $finish;
    end

endmodule

ens/contador.vcd
$date
	Sat Aug 12 23:06:46 2023
$end
$version
	Icarus Verilog
$end
$timescale
	1ps
$end
$scope module testbench_contador $end
$var wire 3 ! count [2:0] $end
$var reg 1 " clk $end
$var reg 1 # rst $end
$scope module contador_inst $end
$var wire 1 " clk $end
$var wire 1 # rst $end
$var reg 3 $ count [2:0] $end
$upscope $end
$upscope $end
$enddefinitions $end
$comment Show the parameter values. $end
$dumpall
$end
#0
$dumpvars
b0 $
1#
0"
b0 !
$end
#5000
1"
#10000
0"
0#
#15000
b1 !
b1 $
1"
#20000
0"
#25000
b10 !
b10 $
1"
#30000
0"
#35000
b11 !
b11 $
1"
#40000
0"
#45000
b100 !
b100 $
1"
#50000
0"
#55000
b101 !
b101 $
1"
#60000
0"
#65000
b110 !
b110 $
1"
#70000
0"
#75000
b111 !
b111 $
1"
#80000
0"
#85000
b0 !
b0 $
1"
#90000
0"
#95000
b1 !
b1 $
1"
#100000
0"
#105000
b10 !
b10 $
1"
#110000
0"
#115000
b11 !
b11 $
1"
#120000
0"
#125000
b100 !
b100 $
1"
